logler_web/__init__.py
logler_web/app.py
logler_web/cli.py
logler_web/static/favicon.svg
logler_web/static/index.html
logler_web/static/assets/index--lnQs9Xg.css
logler_web/static/assets/index-B5A6YkdW.js
logler_web-0.1.0.dist-info/METADATA
logler_web-0.1.0.dist-info/WHEEL
logler_web-0.1.0.dist-info/entry_points.txt
logler_web-0.1.0.dist-info/RECORD
