Metadata-Version: 2.4
Name: logler-web
Version: 0.1.0
Summary: Web interface for logler - log viewing with thread tracking and analysis
Project-URL: Homepage, https://github.com/gabu-quest/logler-web
Project-URL: Documentation, https://github.com/gabu-quest/logler-web#readme
Project-URL: Repository, https://github.com/gabu-quest/logler-web
Author: Logler Contributors
License: MIT
Keywords: debugging,logging,logs,monitoring,viewer,web
Classifier: Development Status :: 3 - Alpha
Classifier: Framework :: FastAPI
Classifier: Intended Audience :: Developers
Classifier: License :: OSI Approved :: MIT License
Classifier: Programming Language :: Python :: 3
Classifier: Programming Language :: Python :: 3.9
Classifier: Programming Language :: Python :: 3.10
Classifier: Programming Language :: Python :: 3.11
Classifier: Programming Language :: Python :: 3.12
Classifier: Topic :: Software Development :: Debuggers
Classifier: Topic :: System :: Logging
Requires-Python: >=3.9
Requires-Dist: fastapi>=0.100.0
Requires-Dist: logler>=1.0.0
Requires-Dist: uvicorn[standard]>=0.20.0
Provides-Extra: dev
Requires-Dist: httpx>=0.28.0; extra == 'dev'
Requires-Dist: pytest>=8.0.0; extra == 'dev'
Requires-Dist: ruff>=0.3.0; extra == 'dev'
